pybench/Arithmetic.py
pybench/Calls.py
pybench/CommandLine.py
pybench/Constructs.py
pybench/Dict.py
pybench/Exceptions.py
pybench/Imports.py
pybench/Instances.py
pybench/Lists.py
pybench/Lookups.py
pybench/NewInstances.py
pybench/Numbers.py
pybench/Setup.py
pybench/Strings.py
pybench/Tuples.py
pybench/Unicode.py
pybench/With.py
pybench/__init__.py
pybench/clockres.py
pybench/pybench.py
pybench/systimes.py
pybench/package/__init__.py
pybench/package/submodule.py
thoth_pybench-0.0.6.dist-info/LICENSE
thoth_pybench-0.0.6.dist-info/METADATA
thoth_pybench-0.0.6.dist-info/WHEEL
thoth_pybench-0.0.6.dist-info/entry_points.txt
thoth_pybench-0.0.6.dist-info/top_level.txt
thoth_pybench-0.0.6.dist-info/RECORD
