Metadata-Version: 2.1
Name: thoth-pybench
Version: 0.0.6
Summary: Adopted PyBench tool to benchmark Python interpreter by the Thoth team.
Home-page: https://openbenchmarking.org/test/pts/pybench
Author: Marc-Andre Lemburg
Author-email: mal@lemburg.com
Maintainer: Francesco Murdaca
Maintainer-email: fmurdaca@redhat.com
License: UNKNOWN
Download-URL: https://github.com/thoth-station/thoth-pybench
Platform: UNKNOWN
